awspub/__init__.py
awspub/api.py
awspub/cli/__init__.py
awspub/common.py
awspub/configmodels.py
awspub/context.py
awspub/exceptions.py
awspub/image.py
awspub/image_marketplace.py
awspub/s3.py
awspub/snapshot.py
awspub/sns.py
awspub/tests/__init__.py
awspub/tests/fixtures/config-invalid-s3-extra.yaml
awspub/tests/fixtures/config-minimal.yaml
awspub/tests/fixtures/config-valid-nonawspub.yaml
awspub/tests/fixtures/config1.vmdk
awspub/tests/fixtures/config1.yaml
awspub/tests/fixtures/config2-mapping.yaml
awspub/tests/fixtures/config2.yaml
awspub/tests/fixtures/config3-duplicate-keys.yaml
awspub/tests/test_api.py
awspub/tests/test_cli.py
awspub/tests/test_common.py
awspub/tests/test_context.py
awspub/tests/test_image.py
awspub/tests/test_image_marketplace.py
awspub/tests/test_s3.py
awspub/tests/test_snapshot.py
awspub/tests/test_sns.py
awspub-0.0.15.dist-info/METADATA
awspub-0.0.15.dist-info/WHEEL
awspub-0.0.15.dist-info/entry_points.txt
awspub-0.0.15.dist-info/licenses/LICENSE
awspub-0.0.15.dist-info/RECORD
